setup.py
django_narrative.egg-info/PKG-INFO
django_narrative.egg-info/SOURCES.txt
django_narrative.egg-info/dependency_links.txt
django_narrative.egg-info/requires.txt
django_narrative.egg-info/top_level.txt
narrative/__init__.py
narrative/admin.py
narrative/api.py
narrative/assertions.py
narrative/checker.py
narrative/escalating_response.py
narrative/events.py
narrative/executor.py
narrative/models.py
narrative/urls.py
narrative/utils.py
narrative/views.py
narrative/batteries/__init__.py
narrative/batteries/models.py
narrative/batteries/uptime.py
narrative/batteries/uptime_tests.py
narrative/management/__init__.py
narrative/management/commands/__init__.py
narrative/management/commands/check_assertions.py
narrative/management/commands/clear_expired_data.py
narrative/management/commands/detect_events.py
narrative/migrations/0001_initial.py
narrative/migrations/0002_auto__add_field_assertionmeta_check_interval_seconds__add_field_assert.py
narrative/migrations/0003_auto__add_field_event_expiration_time.py
narrative/migrations/0004_auto__del_field_event_event_operand_detail__del_field_event_event_oper.py
narrative/migrations/0005_auto__add_datum.py
narrative/migrations/0006_rename_event_to_datum.py
narrative/migrations/0007_auto__del_event.py
narrative/migrations/0008_auto__add_field_assertionmeta_class_load_path.py
narrative/migrations/0009_rename_assertion_load_path_to_class_load_path.py
narrative/migrations/0010_auto__del_field_assertionmeta_assertion_load_path.py
narrative/migrations/0011_auto__add_eventmeta.py
narrative/migrations/0012_auto__add_field_assertionmeta_args.py
narrative/migrations/0013_auto__add_field_solution_error_traceback.py
narrative/migrations/0014_auto__del_unique_assertionmeta_display_name__del_unique_assertionmeta_.py
narrative/migrations/0015_auto__add_field_datum_log_level.py
narrative/migrations/0016_auto__add_narrativeconfig.py
narrative/migrations/0017_create_default_narrative_config.py
narrative/migrations/0018_auto__add_field_resolutionstep_reason.py
narrative/migrations/0019_auto__chg_field_assertionmeta_class_load_path__chg_field_eventmeta_cla.py
narrative/migrations/0020_auto__add_field_eventmeta_args_json.py
