Metadata-Version: 1.0
Name: django-narrative
Version: 0.5.9
Summary: Django narrative
Home-page: https://github.com/
Author: UNKNOWN
Author-email: UNKNOWN
License: UNKNOWN
Platform: UNKNOWN
